odoo/addons/web_filter_header_button/README.rst
odoo/addons/web_filter_header_button/__init__.py
odoo/addons/web_filter_header_button/__manifest__.py
odoo/addons/web_filter_header_button/demo/ir_module_module_view.xml
odoo/addons/web_filter_header_button/i18n/it.po
odoo/addons/web_filter_header_button/i18n/web_filter_header_button.pot
odoo/addons/web_filter_header_button/readme/CONFIGURE.md
odoo/addons/web_filter_header_button/readme/CONTEXT.md
odoo/addons/web_filter_header_button/readme/CONTRIBUTORS.md
odoo/addons/web_filter_header_button/readme/DESCRIPTION.md
odoo/addons/web_filter_header_button/readme/ROADMAP.md
odoo/addons/web_filter_header_button/readme/USAGE.md
odoo/addons/web_filter_header_button/static/description/icon.png
odoo/addons/web_filter_header_button/static/description/index.html
odoo/addons/web_filter_header_button/static/src/control_panel/control_panel.xml
odoo/addons/web_filter_header_button/static/src/control_panel/control_panel_patch.esm.js
odoo/addons/web_filter_header_button/static/src/filter_button/filter_button.esm.js
odoo/addons/web_filter_header_button/static/src/filter_button/filter_button.xml
odoo/addons/web_filter_header_button/static/src/search/search_arch_parser_patch.esm.js
odoo/addons/web_filter_header_button/static/src/search/search_model_patch.esm.js
odoo_addon_web_filter_header_button-18.0.1.0.0.4.dist-info/METADATA
odoo_addon_web_filter_header_button-18.0.1.0.0.4.dist-info/WHEEL
odoo_addon_web_filter_header_button-18.0.1.0.0.4.dist-info/top_level.txt
odoo_addon_web_filter_header_button-18.0.1.0.0.4.dist-info/RECORD
